[
  {
    "category": "청소년",
    "name": "어쩌면 좋아 열네 살",
    "writer": "정병진",
    "company": "별숲",
    "image" : "1.jpg"
  },
  {
    "category": "소설",
    "name": "스프링벅",
    "writer": "배유안",
    "company": "창비",
    "image" : "2.jpg"
  },
  {
    "category": "로맨스",
    "name": "치타 소녀와 좀비 소년",
    "writer": "김영리",
    "company": "라임",
    "image" : "3.jpg"
  },
  {
    "category": "자기계발",
    "name": "성장을 위한 책 읽기",
    "writer": "안광복",
    "company": "학교도서관저널",
    "image" : "4.jpg"
  },
  {
    "category": "인문학",
    "name": "질문하는 십대, 대답하는 인문학",
    "writer": "전규리",
    "company": "풀빛",
    "image" : "5.jpg"
  },
  {
    "category": "예술",
    "name": "인문학, 한옥에 살다",
    "writer": "이상현",
    "company": "채륜서",
    "image" : "6.jpg"
  }
]